<?xml version="1.0"?>
<!DOCTYPE hibernate-mapping PUBLIC "-//Hibernate/Hibernate Mapping DTD 3.0//EN"
"http://hibernate.sourceforge.net/hibernate-mapping-3.0.dtd">
<!-- Generated 16.07.2012 17:29:06 by Hibernate Tools 3.3.0.GA -->
<hibernate-mapping>
    <class name="de.bielefeld.umweltamt.aui.mappings.generated.atl.AtlStatus" table="atl_status" schema="auik">
        <id name="id" type="int">
            <column name="id" />
            <generator class="assigned" />
        </id>
        <property name="bezeichnung" type="string">
            <column name="bezeichnung" />
        </property>
        <set name="atlProbenahmens" table="atl_probenahmen" inverse="true" lazy="true" fetch="select">
            <key>
                <column name="status" />
            </key>
            <one-to-many class="de.bielefeld.umweltamt.aui.mappings.generated.atl.AtlProbenahmen" />
        </set>
    </class>
</hibernate-mapping>
